anson/__init__.py
anson/version.py
anson-0.0.0a0.dist-info/LICENSE
anson-0.0.0a0.dist-info/METADATA
anson-0.0.0a0.dist-info/WHEEL
anson-0.0.0a0.dist-info/top_level.txt
anson-0.0.0a0.dist-info/RECORD
