Metadata-Version: 2.1
Name: anson
Version: 0.0.0a0
Summary: Columnar Data Format
Home-page: https://github.com/mabel-dev/anson/
Author: joocer
Author-email: justin.joyce@joocer.com
Maintainer: Joocer
License-File: LICENSE
Requires-Dist: lz4
